feax/DCboundary.py
feax/__init__.py
feax/assembler.py
feax/basis.py
feax/fe.py
feax/internal_vars.py
feax/mesh.py
feax/problem.py
feax/solver.py
feax/types.py
feax/utils.py
feax/lattice_toolkit/__init__.py
feax/lattice_toolkit/graph.py
feax/lattice_toolkit/pbc.py
feax/lattice_toolkit/solver.py
feax/lattice_toolkit/unitcell.py
feax/lattice_toolkit/utils.py
feax/topopt_toolkit/__init__.py
feax/topopt_toolkit/filter.py
feax/topopt_toolkit/mdmm.py
feax/topopt_toolkit/responses.py
feax-0.0.5.dist-info/licenses/LICENSE
feax-0.0.5.dist-info/METADATA
feax-0.0.5.dist-info/WHEEL
feax-0.0.5.dist-info/top_level.txt
feax-0.0.5.dist-info/RECORD
