Metadata-Version: 2.4
Name: feax
Version: 0.0.5
Summary: A GPU-accelerated finite element analysis framework with JAX.
Author: Naruki-Ichihara
Author-email: Naruki-Ichihara <ichihara.naruki@gmail.com>
Keywords: JAX,CUDA,Simulation,PINN
Classifier: Programming Language :: Python :: 3
Requires-Python: >=3.9
License-File: LICENSE
Requires-Dist: numpy
Requires-Dist: pandas
Requires-Dist: scipy
Requires-Dist: matplotlib
Requires-Dist: meshio
Requires-Dist: pytest
Requires-Dist: fenics-basix
Requires-Dist: gmsh
Dynamic: license-file
